scipyconference/__init__.py
scipyconference/puns.json
scipyconference/puns.py
scipyconference-0.3.dist-info/licenses/LICENSE
scipyconference-0.3.dist-info/METADATA
scipyconference-0.3.dist-info/WHEEL
scipyconference-0.3.dist-info/entry_points.txt
scipyconference-0.3.dist-info/top_level.txt
scipyconference-0.3.dist-info/RECORD
