Metadata-Version: 2.4
Name: scipyconference
Version: 0.3
Requires-Python: >=3.10
License-File: LICENSE
Requires-Dist: numpy
Dynamic: license-file
